{
  "schemaVersion": 1,
  "type": "press-theme",
  "value": "glasswing",
  "label": "Glasswing",
  "version": "0.1.0",
  "contractVersion": 1,
  "release": {
    "tag": "v0.1.0",
    "htmlUrl": "https://github.com/EkilyHQ/Press-Theme-Glasswing/releases/tag/v0.1.0",
    "publishedAt": "2026-05-11T05:04:26Z",
    "notes": ""
  },
  "asset": {
    "name": "press-theme-glasswing-v0.1.0.zip",
    "url": "https://raw.githubusercontent.com/EkilyHQ/Press-Theme-Glasswing/release-artifacts/v0.1.0/press-theme-glasswing-v0.1.0.zip",
    "size": 9295,
    "digest": "sha256:77cf9914ac2f24b5ac6164f31ace323ddc3399430ee35bfb405def0b2682fbbb"
  },
  "files": [
    "modules/glasswing.js",
    "theme.css",
    "theme.json"
  ]
}
